{
  "comforts:sleeping_bag_light_gray": {
    "criteria": {
      "has_the_recipe": "2024-07-02 18:28:09 +0500"
    },
    "done": true
  },
  "tetra:spelunking/find_scroll": {
    "criteria": {
      "find": "2024-07-16 01:28:12 +0500"
    },
    "done": true
  },
  "create:wrench_goggles": {
    "criteria": {
      "1": "2024-07-03 00:04:11 +0500"
    },
    "done": false
  },
  "comforts:hammock_cyan_from_white": {
    "criteria": {
      "has_the_recipe": "2024-07-02 18:28:09 +0500"
    },
    "done": true
  },
  "repurposed_structures:igloos": {
    "criteria": {
      "in_igloo_grassy": "2024-07-02 21:06:27 +0500"
    },
    "done": false
  },
  "comforts:hammock_black": {
    "criteria": {
      "has_the_recipe": "2024-07-02 18:28:09 +0500"
    },
    "done": true
  },
  "comforts:sleeping_bag_light_blue": {
    "criteria": {
      "has_the_recipe": "2024-07-02 18:28:09 +0500"
    },
    "done": true
  },
  "comforts:sleeping_bag_lime": {
    "criteria": {
      "has_the_recipe": "2024-07-02 18:28:09 +0500"
    },
    "done": true
  },
  "minecraft:nether/obtain_crying_obsidian": {
    "criteria": {
      "crying_obsidian": "2024-07-03 00:16:17 +0500"
    },
    "done": true
  },
  "morevillagers:first_village": {
    "criteria": {
      "taiga": "2024-07-03 01:13:55 +0500"
    },
    "done": true
  },
  "farmersdelight:main/harvest_straw": {
    "criteria": {
      "harvest_straw": "2024-08-03 15:32:36 +0500"
    },
    "done": true
  },
  "naturescompass:natures_compass": {
    "criteria": {
      "has_compass": "2024-07-02 18:28:09 +0500"
    },
    "done": true
  },
  "minecraft:adventure/play_jukebox_in_meadows": {
    "criteria": {
      "play_jukebox_in_meadows": "2024-07-17 01:55:10 +0500"
    },
    "done": true
  },
  "comforts:sleeping_bag_lime_from_white": {
    "criteria": {
      "has_the_recipe": "2024-07-02 18:28:09 +0500"
    },
    "done": true
  },
  "quark:get_all_blossom_saplings": {
    "criteria": {
      "blue": "2024-07-02 22:21:22 +0500"
    },
    "done": false
  },
  "mcwroofs:recipes/stone": {
    "criteria": {
      "has_planks": "2024-07-02 20:37:09 +0500"
    },
    "done": true
  },
  "mcwroofs:recipes/jungle": {
    "criteria": {
      "has_planks": "2024-07-17 09:06:02 +0500"
    },
    "done": true
  },
  "minecolonies:production/build_miner": {
    "criteria": {
      "miner": "2024-07-17 05:32:03 +0500"
    },
    "done": true
  },
  "alexsmobs:alexsmobs/alligator_snapping_turtle": {
    "criteria": {
      "killed_by": "2024-07-03 01:12:52 +0500"
    },
    "done": true
  },
  "minecraft:nether/root": {
    "criteria": {
      "entered_nether": "2024-08-03 14:51:43 +0500"
    },
    "done": true
  },
  "tetra:upgrades/repairs": {
    "criteria": {
      "hammer": "2024-07-02 23:04:47 +0500"
    },
    "done": true
  },
  "minecolonies:minecolonies/build_citizen": {
    "criteria": {
      "citizens_hut": "2024-07-17 06:03:11 +0500"
    },
    "done": true
  },
  "minecraft:adventure/hero_of_the_village": {
    "criteria": {
      "hero_of_the_village": "2024-08-03 02:37:21 +0500"
    },
    "done": true
  },
  "create:mechanical_press": {
    "criteria": {
      "0": "2024-07-02 23:28:39 +0500"
    },
    "done": true
  },
  "minecolonies:minecolonies/build_tavern": {
    "criteria": {
      "tavern": "2024-07-17 03:56:14 +0500"
    },
    "done": true
  },
  "mcwroofs:recipes/birch_planks": {
    "criteria": {
      "has_planks": "2024-07-15 06:05:46 +0500"
    },
    "done": true
  },
  "comforts:sleeping_bag_black": {
    "criteria": {
      "has_the_recipe": "2024-07-02 18:28:09 +0500"
    },
    "done": true
  },
  "minecraft:story/shiny_gear": {
    "criteria": {
      "diamond_helmet": "2024-07-02 21:53:40 +0500"
    },
    "done": true
  },
  "tetra:scrolls/find_scroll_key_guard": {
    "criteria": {
      "find": "2024-07-16 01:28:22 +0500"
    },
    "done": true
  },
  "mcwroofs:recipes/oak": {
    "criteria": {
      "has_planks": "2024-07-02 18:40:12 +0500"
    },
    "done": true
  },
  "repurposed_structures:witch_huts": {
    "criteria": {
      "in_witch_hut_birch": "2024-07-02 19:01:27 +0500"
    },
    "done": false
  },
  "create_enchantment_industry:experienced_engineer": {
    "criteria": {
      "have_experience_nugget": "2024-07-02 21:53:21 +0500"
    },
    "done": true
  },
  "croptopia:gather_savanna": {
    "criteria": {
      "kiwi_seed": "2024-08-03 14:43:24 +0500"
    },
    "done": false
  },
  "majruszsdifficulty:recipes/misc/tattered_armor": {
    "criteria": {
      "has_cloth": "2024-08-06 16:17:14 +0500"
    },
    "done": true
  },
  "comforts:hammock_red_from_white": {
    "criteria": {
      "has_the_recipe": "2024-07-02 18:28:09 +0500"
    },
    "done": true
  },
  "tetra:spelunking/root": {
    "criteria": {
      "spelunking": "2024-07-02 23:34:54 +0500"
    },
    "done": true
  },
  "comforts:hammock_yellow": {
    "criteria": {
      "has_the_recipe": "2024-07-02 18:28:09 +0500"
    },
    "done": true
  },
  "mcwfences:recipes/stone": {
    "criteria": {
      "has_stone": "2024-07-02 18:28:09 +0500"
    },
    "done": true
  },
  "minecolonies:production/root": {
    "criteria": {
      "builders_hut": "2024-07-17 01:01:15 +0500"
    },
    "done": true
  },
  "explorerscompass:explorers_compass_cobweb": {
    "criteria": {
      "has_recipe": "2024-07-02 18:28:09 +0500",
      "has_cobweb": "2024-07-02 18:28:09 +0500"
    },
    "done": true
  },
  "mcwroofs:recipes/dark_oak": {
    "criteria": {
      "has_planks": "2024-07-02 22:22:05 +0500"
    },
    "done": true
  },
  "croptopia:gather_all": {
    "criteria": {
      "saguaro_seed": "2024-08-06 16:27:01 +0500",
      "chile_pepper_seed": "2024-08-06 16:27:01 +0500",
      "cabbage_seed": "2024-07-17 07:03:29 +0500",
      "kiwi_seed": "2024-08-03 14:43:24 +0500",
      "artichoke_seed": "2024-08-06 16:27:01 +0500",
      "asparagus_seed": "2024-08-06 16:27:01 +0500"
    },
    "done": false
  },
  "buildersdelight:root": {
    "criteria": {
      "crafting_table": "2024-07-02 18:28:09 +0500"
    },
    "done": true
  },
  "tombstone:adventure/cancel_ghostly_shape": {
    "criteria": {
      "coded_trigger": "2024-07-02 19:30:18 +0500"
    },
    "done": true
  },
  "morevillagers:first_trade": {
    "criteria": {
      "villagertrade": "2024-07-15 05:38:20 +0500"
    },
    "done": true
  },
  "mcwroofs:recipes/spruce": {
    "criteria": {
      "has_planks": "2024-07-02 19:57:15 +0500"
    },
    "done": true
  },
  "comforts:hammock_pink_from_white": {
    "criteria": {
      "has_the_recipe": "2024-07-02 18:28:09 +0500"
    },
    "done": true
  },
  "morevillagers:all_villages": {
    "criteria": {
      "taiga": "2024-07-03 01:13:55 +0500",
      "plains": "2024-08-03 15:12:56 +0500"
    },
    "done": false
  },
  "tombstone:adventure/use_true_sight": {
    "criteria": {
      "has_magic_scroll": "2024-07-17 03:44:18 +0500"
    },
    "done": true
  },
  "betterdungeons:all_dungeons": {
    "criteria": {
      "in_better_spider_dungeon": "2024-07-02 19:26:50 +0500"
    },
    "done": false
  },
  "beautify:frames": {
    "criteria": {
      "requirement": "2024-07-02 19:13:45 +0500"
    },
    "done": true
  },
  "mcwfences:recipes/jungle": {
    "criteria": {
      "has_jungle": "2024-07-02 18:28:09 +0500"
    },
    "done": true
  },
  "tombstone:adventure/bone_crusher": {
    "criteria": {
      "coded_trigger": "2024-07-16 02:24:27 +0500"
    },
    "done": true
  },
  "minecolonies:minecolonies/build_town_hall": {
    "criteria": {
      "town_hall": "2024-07-17 02:44:52 +0500"
    },
    "done": true
  },
  "tombstone:adventure/chain_death": {
    "criteria": {
      "coded_trigger": "2024-07-17 03:41:12 +0500"
    },
    "done": true
  },
  "mcwroofs:recipes/oak_planks": {
    "criteria": {
      "has_planks": "2024-07-02 18:39:36 +0500"
    },
    "done": true
  },
  "alexsmobs:alexsmobs/kangaroo": {
    "criteria": {
      "killed_by": "2024-07-15 04:44:05 +0500"
    },
    "done": true
  },
  "tombstone:adventure/find_grave_dust": {
    "criteria": {
      "from_undead": "2024-07-02 20:38:34 +0500"
    },
    "done": true
  },
  "mcwfences:recipes/spruce": {
    "criteria": {
      "has_spruce": "2024-07-02 18:28:09 +0500"
    },
    "done": true
  },
  "mcwfences:recipes/oak": {
    "criteria": {
      "has_oak": "2024-07-02 18:28:09 +0500"
    },
    "done": true
  },
  "mcwfences:recipes/hedge": {
    "criteria": {
      "has_birch": "2024-07-02 18:28:09 +0500"
    },
    "done": true
  },
  "mcwfences:recipes/end": {
    "criteria": {
      "has_end_brick": "2024-07-02 18:28:09 +0500"
    },
    "done": true
  },
  "comforts:hammock_purple": {
    "criteria": {
      "has_the_recipe": "2024-07-02 18:28:09 +0500"
    },
    "done": true
  },
  "minecraft:husbandry/balanced_diet": {
    "criteria": {
      "baked_potato": "2024-07-02 19:11:58 +0500",
      "abnormals_delight:onion": "2024-07-02 21:15:48 +0500",
      "bread": "2024-07-02 20:08:36 +0500",
      "golden_apple": "2024-07-03 01:02:51 +0500",
      "rotten_flesh": "2024-08-06 02:43:03 +0500",
      "melon_slice": "2024-07-15 04:33:29 +0500",
      "neapolitan:strawberries": "2024-07-02 19:23:22 +0500",
      "abnormals_delight:mixed_salad": "2024-07-02 21:12:51 +0500",
      "cooked_beef": "2024-07-15 05:15:30 +0500",
      "salmon": "2024-07-03 01:03:23 +0500",
      "cooked_chicken": "2024-07-02 22:11:47 +0500",
      "mushroom_stew": "2024-07-02 21:05:15 +0500",
      "cooked_mutton": "2024-07-02 22:12:43 +0500",
      "buzzier_bees:honey_bread": "2024-07-02 18:44:40 +0500",
      "apple": "2024-07-02 18:34:34 +0500",
      "supplementaries:candy": "2024-07-02 21:55:54 +0500",
      "golden_carrot": "2024-07-03 00:05:18 +0500",
      "enchanted_golden_apple": "2024-08-02 19:39:09 +0500"
    },
    "done": false
  },
  "croptopia:frying_pan": {
    "criteria": {
      "frying_pan": "2024-07-16 00:27:39 +0500"
    },
    "done": true
  },
  "croptopia:food_press": {
    "criteria": {
      "food_press": "2024-07-16 01:00:15 +0500"
    },
    "done": true
  },
  "takesapillage:pillager_camp": {
    "criteria": {
      "in_pillager_camp": "2024-07-03 01:00:56 +0500"
    },
    "done": true
  },
  "comforts:hammock_lime": {
    "criteria": {
      "has_the_recipe": "2024-07-02 18:28:10 +0500"
    },
    "done": true
  },
  "comforts:sleeping_bag_pink": {
    "criteria": {
      "has_the_recipe": "2024-07-02 18:28:09 +0500"
    },
    "done": true
  },
  "majruszsdifficulty:progressive_difficulty/warden_treasure_bag": {
    "criteria": {
      "bag_opened": "2024-07-17 03:42:01 +0500"
    },
    "done": true
  },
  "naturescompass:natures_compass_sapling": {
    "criteria": {
      "has_recipe": "2024-07-02 18:28:09 +0500"
    },
    "done": true
  },
  "alexsmobs:alexsmobs/rattlesnake": {
    "criteria": {
      "killed_by": "2024-08-06 16:49:15 +0500"
    },
    "done": true
  },
  "alexsmobs:alexsmobs/murmur": {
    "criteria": {
      "killed_by": "2024-07-02 21:31:58 +0500"
    },
    "done": true
  },
  "comforts:sleeping_bag_light_blue_from_white": {
    "criteria": {
      "has_the_recipe": "2024-07-02 18:28:09 +0500"
    },
    "done": true
  },
  "beautify:trellis": {
    "criteria": {
      "requirement": "2024-07-02 18:36:33 +0500"
    },
    "done": true
  },
  "tombstone:adventure/fortuitous_militia": {
    "criteria": {
      "coded_trigger": "2024-07-02 21:49:21 +0500"
    },
    "done": true
  },
  "minecolonies:production/build_farmer": {
    "criteria": {
      "farmer": "2024-07-17 06:16:58 +0500"
    },
    "done": true
  },
  "minecraft:adventure/avoid_vibration": {
    "criteria": {
      "avoid_vibration": "2024-07-17 03:37:44 +0500"
    },
    "done": true
  },
  "immersive_melodies:misc/instruments": {
    "criteria": {
      "has_item": "2024-07-02 19:10:08 +0500"
    },
    "done": true
  },
  "comforts:hammock_magenta": {
    "criteria": {
      "has_the_recipe": "2024-07-02 18:28:09 +0500"
    },
    "done": true
  },
  "productivebees:husbandry/bee_cage/overworld_nest": {
    "criteria": {
      "get_item": "2024-07-15 05:51:15 +0500"
    },
    "done": true
  },
  "idas:idas_root": {
    "criteria": {
      "always": "2024-07-02 18:28:23 +0500"
    },
    "done": true
  },
  "chalk:adventure/sleep_three_times_in_one_place": {
    "criteria": {
      "sleep_three_times_in_one_place": "2024-07-02 22:31:12 +0500"
    },
    "done": true
  },
  "minecolonies:minecolonies/citizen_eat_food_first": {
    "criteria": {
      "citizen_eat_anything": "2024-07-20 00:27:14 +0500"
    },
    "done": true
  },
  "comforts:sleeping_bag_red": {
    "criteria": {
      "has_the_recipe": "2024-07-02 18:28:09 +0500"
    },
    "done": true
  },
  "minecraft:husbandry/bred_all_animals": {
    "criteria": {
      "minecraft:sheep": "2024-07-17 04:59:29 +0500"
    },
    "done": false
  },
  "takesapillage:root": {
    "criteria": {
      "always": "2024-07-02 18:28:23 +0500"
    },
    "done": true
  },
  "minecraft:story/obtain_armor": {
    "criteria": {
      "iron_helmet": "2024-07-02 18:48:00 +0500"
    },
    "done": true
  },
  "comforts:sleeping_bag_blue": {
    "criteria": {
      "has_the_recipe": "2024-07-02 18:28:09 +0500"
    },
    "done": true
  },
  "minecraft:story/mine_stone": {
    "criteria": {
      "get_stone": "2024-07-02 18:39:59 +0500"
    },
    "done": true
  },
  "mcwroofs:recipes/acacia": {
    "criteria": {
      "has_planks": "2024-08-05 23:09:47 +0500"
    },
    "done": true
  },
  "beautify:lamps": {
    "criteria": {
      "requirement": "2024-07-02 19:10:08 +0500"
    },
    "done": true
  },
  "alexsmobs:alexsmobs/grizzly_bear": {
    "criteria": {
      "killed_by": "2024-07-02 21:19:29 +0500"
    },
    "done": true
  },
  "morevillagers:root": {
    "criteria": {
      "always": "2024-07-02 18:28:23 +0500"
    },
    "done": true
  },
  "tombstone:adventure/create_magic_scroll": {
    "criteria": {
      "has_magic_scroll": "2024-07-02 21:02:59 +0500"
    },
    "done": true
  },
  "create:andesite_casing": {
    "criteria": {
      "0": "2024-07-02 23:11:43 +0500"
    },
    "done": true
  },
  "tombstone:adventure/strong_or_careful": {
    "criteria": {
      "coded_trigger": "2024-07-17 02:30:22 +0500"
    },
    "done": true
  },
  "minecraft:adventure/sleep_in_bed": {
    "criteria": {
      "slept_in_bed": "2024-07-02 19:04:45 +0500"
    },
    "done": true
  },
  "tetra:spelunking/find_scroll_sturdy": {
    "criteria": {
      "find": "2024-07-16 01:28:21 +0500"
    },
    "done": true
  },
  "minecolonies:minecolonies/root": {
    "criteria": {
      "supply_ship_placed": "2024-07-17 00:09:05 +0500"
    },
    "done": true
  },
  "comforts:sleeping_bag_orange": {
    "criteria": {
      "has_the_recipe": "2024-07-02 18:28:09 +0500"
    },
    "done": true
  },
  "minecraft:husbandry/root": {
    "criteria": {
      "consumed_item": "2024-07-02 18:34:34 +0500"
    },
    "done": true
  },
  "mcwfences:recipes/nether": {
    "criteria": {
      "has_nether_brick": "2024-07-02 18:28:09 +0500"
    },
    "done": true
  },
  "mcwroofs:recipes/acacia_planks": {
    "criteria": {
      "has_planks": "2024-07-20 00:26:51 +0500"
    },
    "done": true
  },
  "mcwfences:recipes/crimson": {
    "criteria": {
      "has_crimson": "2024-07-02 18:28:09 +0500"
    },
    "done": true
  },
  "minecraft:adventure/root": {
    "criteria": {
      "killed_something": "2024-07-02 18:43:07 +0500"
    },
    "done": true
  },
  "croptopia:gather_food": {
    "criteria": {
      "sea_lettuce": "2024-07-15 05:32:14 +0500",
      "hamburger": "2024-07-16 00:27:57 +0500",
      "clam": "2024-07-15 05:33:47 +0500",
      "toast": "2024-08-02 19:33:57 +0500",
      "cooked_tuna": "2024-07-15 05:32:04 +0500",
      "tuna": "2024-07-15 05:32:04 +0500"
    },
    "done": false
  },
  "mcwfences:recipes/bamboo": {
    "criteria": {
      "has_bamboo": "2024-07-02 18:28:09 +0500"
    },
    "done": true
  },
  "mcwfences:recipes/prismarine": {
    "criteria": {
      "has_qq": "2024-07-02 18:28:09 +0500"
    },
    "done": true
  },
  "comforts:hammock_red": {
    "criteria": {
      "has_the_recipe": "2024-07-02 18:28:10 +0500"
    },
    "done": true
  },
  "farmersdelight:main/root": {
    "criteria": {
      "seeds": "2024-07-02 18:28:09 +0500"
    },
    "done": true
  },
  "comforts:hammock_black_from_white": {
    "criteria": {
      "has_the_recipe": "2024-07-02 18:28:09 +0500"
    },
    "done": true
  },
  "minecolonies:minecolonies/start_builder": {
    "criteria": {
      "builder_request": "2024-07-17 00:25:06 +0500"
    },
    "done": true
  },
  "minecolonies:minecolonies/build_guard_tower": {
    "criteria": {
      "guard_tower": "2024-07-17 05:46:34 +0500"
    },
    "done": true
  },
  "tombstone:adventure/village_defender": {
    "criteria": {
      "coded_trigger": "2024-07-16 01:48:40 +0500"
    },
    "done": true
  },
  "minecolonies:minecolonies/build_builder_2": {
    "criteria": {
      "builders_hut": "2024-07-17 04:38:02 +0500"
    },
    "done": true
  },
  "comforts:hammock_gray_from_white": {
    "criteria": {
      "has_the_recipe": "2024-07-02 18:28:09 +0500"
    },
    "done": true
  },
  "beautify:lamp_jar": {
    "criteria": {
      "requirement": "2024-07-02 20:24:57 +0500"
    },
    "done": true
  },
  "tetra:scrolls/root": {
    "criteria": {
      "find": "2024-07-16 01:28:12 +0500"
    },
    "done": true
  },
  "minecraft:adventure/kill_all_mobs": {
    "criteria": {
      "minecraft:pillager": "2024-07-02 20:48:36 +0500",
      "minecraft:skeleton": "2024-07-02 18:43:07 +0500",
      "minecraft:ravager": "2024-07-03 01:03:49 +0500",
      "minecraft:vindicator": "2024-07-03 01:01:19 +0500",
      "minecraft:spider": "2024-07-02 18:45:28 +0500",
      "minecraft:creeper": "2024-07-02 18:49:24 +0500",
      "quark:forgotten": "2024-07-16 02:39:25 +0500",
      "minecraft:phantom": "2024-08-03 14:37:25 +0500",
      "minecraft:witch": "2024-07-03 00:04:46 +0500",
      "minecraft:wither_skeleton": "2024-08-03 14:54:25 +0500",
      "minecraft:husk": "2024-08-06 16:17:13 +0500",
      "minecraft:cave_spider": "2024-07-02 19:27:05 +0500",
      "quark:wraith": "2024-07-02 21:50:48 +0500",
      "minecraft:silverfish": "2024-07-02 23:53:16 +0500",
      "minecraft:stray": "2024-07-17 02:23:48 +0500",
      "minecraft:vex": "2024-08-03 02:35:26 +0500",
      "minecraft:zombie": "2024-07-02 18:50:36 +0500",
      "minecraft:drowned": "2024-07-16 02:23:54 +0500",
      "minecraft:zombie_villager": "2024-07-02 23:35:58 +0500"
    },
    "done": false
  },
  "mcwfences:recipes/quartz": {
    "criteria": {
      "has_qq": "2024-07-02 18:28:09 +0500"
    },
    "done": true
  },
  "minecraft:story/enter_the_nether": {
    "criteria": {
      "entered_nether": "2024-08-03 14:51:43 +0500"
    },
    "done": true
  },
  "tetra:spelunking/find_scroll_howling": {
    "criteria": {
      "find": "2024-07-16 01:28:15 +0500"
    },
    "done": true
  },
  "minecolonies:production/build_all_herders": {
    "criteria": {
      "chickens": "2024-08-06 01:10:24 +0500",
      "pigs": "2024-08-08 00:13:42 +0500",
      "cows": "2024-08-06 19:25:09 +0500",
      "sheep": "2024-08-06 00:21:26 +0500"
    },
    "done": false
  },
  "minecraft:husbandry/safely_harvest_honey": {
    "criteria": {
      "safely_harvest_honey": "2024-07-16 01:23:00 +0500"
    },
    "done": true
  },
  "minecraft:adventure/trade": {
    "criteria": {
      "traded": "2024-07-15 05:38:20 +0500"
    },
    "done": true
  },
  "tetra:spelunking/find_scroll_throwing": {
    "criteria": {
      "find": "2024-07-16 01:28:14 +0500"
    },
    "done": true
  },
  "comforts:hammock_lime_from_white": {
    "criteria": {
      "has_the_recipe": "2024-07-02 18:28:09 +0500"
    },
    "done": true
  },
  "minecolonies:minecolonies/check_out_guide": {
    "criteria": {
      "click_gui_button_close": "2024-07-02 19:58:12 +0500"
    },
    "done": true
  },
  "comforts:hammock_orange_from_white": {
    "criteria": {
      "has_the_recipe": "2024-07-02 18:28:09 +0500"
    },
    "done": true
  },
  "mcwroofs:recipes/granite": {
    "criteria": {
      "has_planks": "2024-08-03 04:19:34 +0500"
    },
    "done": true
  },
  "minecraft:adventure/voluntary_exile": {
    "criteria": {
      "voluntary_exile": "2024-07-02 21:37:17 +0500"
    },
    "done": true
  },
  "morevillagers:all_workstations_get": {
    "criteria": {
      "barrel": "2024-07-17 02:47:48 +0500",
      "cartographytable": "2024-08-06 17:21:42 +0500",
      "brewingstand": "2024-08-06 17:15:37 +0500",
      "smithingtable": "2024-07-02 22:18:04 +0500",
      "blastfurnace": "2024-08-02 23:01:43 +0500",
      "stonecutter": "2024-08-06 00:51:06 +0500",
      "cauldron": "2024-08-06 17:11:54 +0500"
    },
    "done": false
  },
  "morevillagers:all_professions_traded": {
    "criteria": {
      "fletcher": "2024-08-03 02:37:47 +0500",
      "librarian": "2024-08-05 22:04:38 +0500"
    },
    "done": false
  },
  "comforts:sleeping_bag_light_gray_from_white": {
    "criteria": {
      "has_the_recipe": "2024-07-02 18:28:09 +0500"
    },
    "done": true
  },
  "toms_storage:unlock_chest": {
    "criteria": {
      "inv_changed-chest": "2024-07-02 18:28:09 +0500"
    },
    "done": true
  },
  "create:root": {
    "criteria": {
      "0": "2024-07-02 18:28:09 +0500"
    },
    "done": true
  },
  "betterdeserttemples:root": {
    "criteria": {
      "always": "2024-07-02 18:28:23 +0500"
    },
    "done": true
  },
  "majruszsdifficulty:progressive_difficulty/undead_army_treasure_bag": {
    "criteria": {
      "bag_opened": "2024-08-06 16:28:28 +0500"
    },
    "done": true
  },
  "naturescompass:natures_compass_log": {
    "criteria": {
      "has_recipe": "2024-07-02 18:28:09 +0500"
    },
    "done": true
  },
  "tombstone:adventure/first_knowledge": {
    "criteria": {
      "coded_trigger": "2024-07-02 20:35:01 +0500"
    },
    "done": true
  },
  "minecraft:story/mine_diamond": {
    "criteria": {
      "diamond": "2024-07-02 21:53:19 +0500"
    },
    "done": true
  },
  "minecraft:story/upgrade_tools": {
    "criteria": {
      "stone_pickaxe": "2024-07-02 18:28:09 +0500"
    },
    "done": true
  },
  "croptopia:getseeds": {
    "criteria": {
      "has_seeds": "2024-07-17 07:03:29 +0500"
    },
    "done": true
  },
  "morevillagers:kill_villager": {
    "criteria": {
      "killedvillager": "2024-07-17 03:13:31 +0500"
    },
    "done": true
  },
  "alexsmobs:alexsmobs/root": {
    "criteria": {
      "useitem": "2024-07-02 21:41:36 +0500"
    },
    "done": true
  },
  "tetra:upgrades/workbench": {
    "criteria": {
      "hammer": "2024-07-02 23:04:49 +0500"
    },
    "done": true
  },
  "repurposed_structures:monuments": {
    "criteria": {
      "in_monument_jungle": "2024-07-03 01:33:25 +0500"
    },
    "done": false
  },
  "comforts:hammock_blue": {
    "criteria": {
      "has_the_recipe": "2024-07-02 18:28:09 +0500"
    },
    "done": true
  },
  "farmersdelight:main/eat_comfort_food": {
    "criteria": {
      "comfort": "2024-07-02 21:05:15 +0500"
    },
    "done": true
  },
  "supplementaries:adventure/way_sign": {
    "criteria": {
      "bastion": "2024-07-02 20:44:01 +0500"
    },
    "done": true
  },
  "comforts:hammock_gray": {
    "criteria": {
      "has_the_recipe": "2024-07-02 18:28:10 +0500"
    },
    "done": true
  },
  "betterdungeons:spider_dungeon": {
    "criteria": {
      "in_better_spider_dungeon": "2024-07-02 19:26:50 +0500"
    },
    "done": true
  },
  "minecolonies:minecolonies/build_builder": {
    "criteria": {
      "builders_hut": "2024-07-17 01:01:15 +0500"
    },
    "done": true
  },
  "mcwroofs:recipes/diorite": {
    "criteria": {
      "has_planks": "2024-08-03 04:19:51 +0500"
    },
    "done": true
  },
  "tetra:recipes/workbench": {
    "criteria": {
      "hammer": "2024-07-02 23:04:49 +0500"
    },
    "done": true
  },
  "beautify:progression/root": {
    "criteria": {
      "Install": "2024-07-02 18:28:23 +0500"
    },
    "done": true
  },
  "mcwroofs:recipes/sandstone": {
    "criteria": {
      "has_planks": "2024-08-03 02:13:26 +0500"
    },
    "done": true
  },
  "mcwroofs:recipes/nether_bricks": {
    "criteria": {
      "has_planks": "2024-08-03 03:48:17 +0500"
    },
    "done": true
  },
  "minecraft:husbandry/tame_an_animal": {
    "criteria": {
      "tamed_animal": "2024-07-02 19:03:56 +0500"
    },
    "done": true
  },
  "tombstone:adventure/neighborhood_brawl": {
    "criteria": {
      "coded_trigger": "2024-07-17 03:13:31 +0500"
    },
    "done": true
  },
  "comforts:hammock_white": {
    "criteria": {
      "has_the_recipe": "2024-07-02 18:28:09 +0500"
    },
    "done": true
  },
  "tetra:upgrades/root": {
    "criteria": {
      "hammer": "2024-07-02 23:04:47 +0500"
    },
    "done": true
  },
  "farmersdelight:main/master_chef": {
    "criteria": {
      "mixed_salad": "2024-07-02 21:12:51 +0500"
    },
    "done": false
  },
  "farmersdelight:main/plant_all_crops": {
    "criteria": {
      "kelp": "2024-07-17 08:44:33 +0500",
      "sugar_cane": "2024-07-20 00:20:32 +0500"
    },
    "done": false
  },
  "comforts:sleeping_bag_green_from_white": {
    "criteria": {
      "has_the_recipe": "2024-07-02 18:28:09 +0500"
    },
    "done": true
  },
  "mcwfences:recipes/deepslate": {
    "criteria": {
      "has_deepslate": "2024-07-02 18:28:09 +0500"
    },
    "done": true
  },
  "supplementaries:adventure/globe": {
    "criteria": {
      "unlock": "2024-08-06 01:48:07 +0500"
    },
    "done": true
  },
  "croptopia:mortar_and_pestle": {
    "criteria": {
      "mortar_and_pestle": "2024-07-16 01:00:42 +0500"
    },
    "done": true
  },
  "tombstone:adventure/ashes_and_bones": {
    "criteria": {
      "coded_trigger": "2024-07-02 20:35:01 +0500"
    },
    "done": true
  },
  "create:copper": {
    "criteria": {
      "0": "2024-07-02 19:10:08 +0500"
    },
    "done": true
  },
  "create:andesite_alloy": {
    "criteria": {
      "0": "2024-07-02 23:02:37 +0500"
    },
    "done": true
  },
  "mcwroofs:recipes/mangrove": {
    "criteria": {
      "has_planks": "2024-07-02 19:00:30 +0500"
    },
    "done": true
  },
  "comforts:sleeping_bag_black_from_white": {
    "criteria": {
      "has_the_recipe": "2024-07-02 18:28:09 +0500"
    },
    "done": true
  },
  "mcwroofs:recipes/stone_bricks": {
    "criteria": {
      "has_planks": "2024-07-02 20:37:09 +0500"
    },
    "done": true
  },
  "tetra:scrolls/find_scroll_compound_string": {
    "criteria": {
      "find": "2024-07-16 01:28:12 +0500"
    },
    "done": true
  },
  "minecolonies:minecolonies/colony_population_10": {
    "criteria": {
      "population_10": "2024-07-17 09:40:53 +0500"
    },
    "done": true
  },
  "mcwfences:recipes/sandstone": {
    "criteria": {
      "has_sand": "2024-07-02 18:28:09 +0500"
    },
    "done": true
  },
  "nourished_nether:nourished_nether_root": {
    "criteria": {
      "nourished_nether_root": "2024-08-03 14:51:43 +0500"
    },
    "done": true
  },
  "comforts:hammock_light_blue_from_white": {
    "criteria": {
      "has_the_recipe": "2024-07-02 18:28:09 +0500"
    },
    "done": true
  },
  "mcwfences:recipes/mud_brick": {
    "criteria": {
      "has_qq": "2024-07-02 18:28:09 +0500"
    },
    "done": true
  },
  "mcwroofs:recipes/gutters": {
    "criteria": {
      "has_planks": "2024-07-02 18:54:37 +0500"
    },
    "done": true
  },
  "minecraft:nether/find_fortress": {
    "criteria": {
      "in_better_fortress": "2024-08-03 14:51:52 +0500"
    },
    "done": true
  },
  "beautify:rope": {
    "criteria": {
      "requirement": "2024-07-02 18:45:29 +0500"
    },
    "done": true
  },
  "croptopia:gather_swamp": {
    "criteria": {
      "asparagus_seed": "2024-08-06 16:27:01 +0500",
      "artichoke_seed": "2024-08-06 16:27:01 +0500"
    },
    "done": false
  },
  "toms_storage:unlock_netherite": {
    "criteria": {
      "inv_changed-netherite": "2024-07-02 18:28:09 +0500"
    },
    "done": true
  },
  "mcwroofs:recipes/cobblestone": {
    "criteria": {
      "has_planks": "2024-07-02 18:39:59 +0500"
    },
    "done": true
  },
  "beautify:botanist_workbench": {
    "criteria": {
      "requirement": "2024-07-17 07:31:45 +0500"
    },
    "done": true
  },
  "mcwfences:recipes/mangrove": {
    "criteria": {
      "has_mangrove": "2024-07-02 18:28:09 +0500"
    },
    "done": true
  },
  "beautify:candleabras": {
    "criteria": {
      "requirement": "2024-07-02 23:08:11 +0500"
    },
    "done": true
  },
  "mcwfences:recipes/warped": {
    "criteria": {
      "has_warped": "2024-07-02 18:28:09 +0500"
    },
    "done": true
  },
  "comforts:hammock_cyan": {
    "criteria": {
      "has_the_recipe": "2024-07-02 18:28:09 +0500"
    },
    "done": true
  },
  "comforts:sleeping_bag_purple": {
    "criteria": {
      "has_the_recipe": "2024-07-02 18:28:09 +0500"
    },
    "done": true
  },
  "quark:get_all_corundum": {
    "criteria": {
      "red": "2024-07-03 00:11:55 +0500"
    },
    "done": false
  },
  "minecraft:story/deflect_arrow": {
    "criteria": {
      "deflected_projectile": "2024-07-15 04:36:04 +0500"
    },
    "done": true
  },
  "croptopia:knife": {
    "criteria": {
      "knife": "2024-07-16 00:28:28 +0500"
    },
    "done": true
  },
  "croptopia:gather_plains": {
    "criteria": {
      "chile_pepper_seed": "2024-08-06 16:27:01 +0500",
      "cabbage_seed": "2024-07-17 07:03:29 +0500"
    },
    "done": false
  },
  "farmersdelight:main/get_fd_seed": {
    "criteria": {
      "onion": "2024-07-02 21:03:22 +0500"
    },
    "done": true
  },
  "tetra:upgrades/double_headed": {
    "criteria": {
      "hammer": "2024-07-02 23:04:47 +0500"
    },
    "done": true
  },
  "comforts:sleeping_bag_purple_from_white": {
    "criteria": {
      "has_the_recipe": "2024-07-02 18:28:09 +0500"
    },
    "done": true
  },
  "tombstone:adventure/root": {
    "criteria": {
      "auto": "2024-07-02 18:28:25 +0500"
    },
    "done": true
  },
  "comforts:sleeping_bag_yellow": {
    "criteria": {
      "has_the_recipe": "2024-07-02 18:28:09 +0500"
    },
    "done": true
  },
  "morevillagers:buy_map": {
    "criteria": {
      "trade": "2024-07-15 05:38:20 +0500"
    },
    "done": true
  },
  "chalk:adventure/get_skeleton_skull": {
    "criteria": {
      "slept_in_bed": "2024-07-02 21:52:49 +0500"
    },
    "done": true
  },
  "comforts:hammock_light_gray": {
    "criteria": {
      "has_the_recipe": "2024-07-02 18:28:09 +0500"
    },
    "done": true
  },
  "minecolonies:production/build_warehouse": {
    "criteria": {
      "warehouse": "2024-07-17 09:09:38 +0500"
    },
    "done": true
  },
  "productivebees:husbandry/bee_cage": {
    "criteria": {
      "get_item": "2024-07-20 00:19:11 +0500"
    },
    "done": true
  },
  "mcwfences:recipes/birch": {
    "criteria": {
      "has_birch": "2024-07-02 18:28:09 +0500"
    },
    "done": true
  },
  "comforts:sleeping_bag_orange_from_white": {
    "criteria": {
      "has_the_recipe": "2024-07-02 18:28:09 +0500"
    },
    "done": true
  },
  "comforts:hammock_yellow_from_white": {
    "criteria": {
      "has_the_recipe": "2024-07-02 18:28:09 +0500"
    },
    "done": true
  },
  "idas:enchantingtower": {
    "criteria": {
      "in_enchantingtower": "2024-07-02 21:20:30 +0500"
    },
    "done": true
  },
  "comforts:sleeping_bag_blue_from_white": {
    "criteria": {
      "has_the_recipe": "2024-07-02 18:28:09 +0500"
    },
    "done": true
  },
  "comforts:sleeping_bag_green": {
    "criteria": {
      "has_the_recipe": "2024-07-02 18:28:09 +0500"
    },
    "done": true
  },
  "comforts:sleeping_bag_brown_from_white": {
    "criteria": {
      "has_the_recipe": "2024-07-02 18:28:09 +0500"
    },
    "done": true
  },
  "minecraft:story/iron_tools": {
    "criteria": {
      "iron_pickaxe": "2024-07-02 20:52:46 +0500"
    },
    "done": true
  },
  "comforts:sleeping_bag_white": {
    "criteria": {
      "has_the_recipe": "2024-07-02 18:28:09 +0500"
    },
    "done": true
  },
  "comforts:hammock_light_gray_from_white": {
    "criteria": {
      "has_the_recipe": "2024-07-02 18:28:09 +0500"
    },
    "done": true
  },
  "mcwroofs:recipes/red_nether_bricks": {
    "criteria": {
      "has_planks": "2024-07-17 08:38:32 +0500"
    },
    "done": true
  },
  "comforts:sleeping_bag_gray": {
    "criteria": {
      "has_the_recipe": "2024-07-02 18:28:09 +0500"
    },
    "done": true
  },
  "comforts:sleeping_bag_brown": {
    "criteria": {
      "has_the_recipe": "2024-07-02 18:28:09 +0500"
    },
    "done": true
  },
  "tetra:scrolls/find_scroll_halberd": {
    "criteria": {
      "find": "2024-07-16 01:28:21 +0500"
    },
    "done": true
  },
  "minecraft:story/root": {
    "criteria": {
      "crafting_table": "2024-07-02 18:38:55 +0500"
    },
    "done": true
  },
  "majruszsdifficulty:progressive_difficulty/pillager_treasure_bag": {
    "criteria": {
      "bag_opened": "2024-08-03 03:02:26 +0500"
    },
    "done": true
  },
  "mcwroofs:recipes/dark_oak_planks": {
    "criteria": {
      "has_planks": "2024-07-03 00:18:14 +0500"
    },
    "done": true
  },
  "minecolonies:minecolonies/build_mysticalsite": {
    "criteria": {
      "mysticalsite": "2024-08-08 00:47:25 +0500"
    },
    "done": true
  },
  "tetra:recipes/string": {
    "criteria": {
      "got_string": "2024-07-02 18:45:29 +0500"
    },
    "done": true
  },
  "comforts:hammock_light_blue": {
    "criteria": {
      "has_the_recipe": "2024-07-02 18:28:09 +0500"
    },
    "done": true
  },
  "minecraft:story/form_obsidian": {
    "criteria": {
      "obsidian": "2024-07-03 00:13:40 +0500"
    },
    "done": true
  },
  "minecolonies:production/build_lumberjack": {
    "criteria": {
      "lumberjack": "2024-07-17 04:12:50 +0500"
    },
    "done": true
  },
  "comforts:rope_and_nail": {
    "criteria": {
      "has_the_recipe": "2024-07-02 18:28:09 +0500"
    },
    "done": true
  },
  "mcwroofs:recipes/birch": {
    "criteria": {
      "has_planks": "2024-07-15 23:52:40 +0500"
    },
    "done": true
  },
  "idas:ruins_of_the_deep": {
    "criteria": {
      "in_ruins_of_the_deep": "2024-07-16 02:17:27 +0500"
    },
    "done": true
  },
  "beautify:blinds": {
    "criteria": {
      "requirement": "2024-07-02 18:36:33 +0500"
    },
    "done": true
  },
  "minecolonies:minecraft/craft_supply": {
    "criteria": {
      "supply_ship": "2024-07-17 00:09:05 +0500"
    },
    "done": true
  },
  "betterdungeons:root": {
    "criteria": {
      "always": "2024-07-02 18:28:23 +0500"
    },
    "done": true
  },
  "explorerscompass:explorers_compass_cracked_stone_bricks": {
    "criteria": {
      "has_recipe": "2024-07-02 18:28:09 +0500",
      "has_cracked_stone_bricks": "2024-07-02 18:28:09 +0500"
    },
    "done": true
  },
  "comforts:sleeping_bag_red_from_white": {
    "criteria": {
      "has_the_recipe": "2024-07-02 18:28:09 +0500"
    },
    "done": true
  },
  "minecraft:adventure/kill_a_mob": {
    "criteria": {
      "minecraft:skeleton": "2024-07-02 18:43:07 +0500"
    },
    "done": true
  },
  "beautify:iron_blinds": {
    "criteria": {
      "requirement": "2024-07-02 18:54:37 +0500"
    },
    "done": true
  },
  "alexsmobs:alexsmobs/seagull_steal": {
    "criteria": {
      "ex": "2024-07-03 01:30:04 +0500"
    },
    "done": true
  },
  "alexsmobs:alexsmobs/orcas_might": {
    "criteria": {
      "all_effects": "2024-07-03 01:08:39 +0500"
    },
    "done": true
  },
  "comforts:sleeping_bag_magenta_from_white": {
    "criteria": {
      "has_the_recipe": "2024-07-02 18:28:09 +0500"
    },
    "done": true
  },
  "comforts:hammock_magenta_from_white": {
    "criteria": {
      "has_the_recipe": "2024-07-02 18:28:10 +0500"
    },
    "done": true
  },
  "comforts:hammock_brown_from_white": {
    "criteria": {
      "has_the_recipe": "2024-07-02 18:28:09 +0500"
    },
    "done": true
  },
  "tombstone:recipes/from_grave_dust": {
    "criteria": {
      "has_ingredient": "2024-07-02 19:30:33 +0500"
    },
    "done": true
  },
  "toms_storage:unlock_glowstone": {
    "criteria": {
      "inv_changed-glowstone": "2024-07-02 18:28:09 +0500"
    },
    "done": true
  },
  "mcwfences:recipes/blackstone": {
    "criteria": {
      "has_blackstone": "2024-07-02 18:28:09 +0500"
    },
    "done": true
  },
  "minecraft:adventure/ol_betsy": {
    "criteria": {
      "shot_crossbow": "2024-07-02 18:46:33 +0500"
    },
    "done": true
  },
  "minecraft:nether/obtain_blaze_rod": {
    "criteria": {
      "blaze_rod": "2024-08-03 14:56:03 +0500"
    },
    "done": true
  },
  "majruszsdifficulty:progressive_difficulty/normal_mode": {
    "criteria": {
      "game_state": "2024-07-02 18:28:09 +0500"
    },
    "done": true
  },
  "minecolonies:production/build_fisherman": {
    "criteria": {
      "fisherman": "2024-08-06 02:15:34 +0500"
    },
    "done": true
  },
  "quark:get_forgotten_hat": {
    "criteria": {
      "get_forgotten_hat": "2024-07-16 02:39:55 +0500"
    },
    "done": true
  },
  "minecraft:adventure/adventuring_time": {
    "criteria": {
      "minecraft:snowy_slopes": "2024-07-16 00:30:00 +0500",
      "minecraft:old_growth_pine_taiga": "2024-07-03 01:17:28 +0500",
      "minecraft:mushroom_fields": "2024-07-15 05:51:00 +0500",
      "minecraft:taiga": "2024-07-02 19:15:44 +0500",
      "minecraft:frozen_river": "2024-08-03 02:11:58 +0500",
      "minecraft:sunflower_plains": "2024-07-16 02:05:43 +0500",
      "minecraft:birch_forest": "2024-07-02 18:56:08 +0500",
      "minecraft:bamboo_jungle": "2024-08-06 01:33:53 +0500",
      "minecraft:badlands": "2024-07-15 04:40:07 +0500",
      "minecraft:beach": "2024-08-06 16:43:37 +0500",
      "minecraft:stony_peaks": "2024-07-02 21:09:15 +0500",
      "minecraft:dark_forest": "2024-07-17 07:08:47 +0500",
      "minecraft:sparse_jungle": "2024-07-15 04:40:04 +0500",
      "minecraft:river": "2024-07-02 19:16:49 +0500",
      "minecraft:lukewarm_ocean": "2024-07-03 01:24:46 +0500",
      "minecraft:stony_shore": "2024-07-15 05:43:22 +0500",
      "minecraft:snowy_plains": "2024-08-03 02:12:00 +0500",
      "minecraft:dripstone_caves": "2024-07-02 23:53:55 +0500",
      "autumnity:maple_forest": "2024-07-02 18:32:20 +0500",
      "minecraft:swamp": "2024-07-03 00:37:36 +0500",
      "minecraft:jagged_peaks": "2024-07-16 00:30:11 +0500",
      "autumnity:pumpkin_fields": "2024-07-02 18:31:24 +0500",
      "minecraft:cold_ocean": "2024-07-03 01:06:33 +0500",
      "minecraft:forest": "2024-07-02 19:02:47 +0500",
      "minecraft:deep_cold_ocean": "2024-07-03 01:23:23 +0500",
      "minecraft:ice_spikes": "2024-08-03 02:11:28 +0500",
      "minecraft:frozen_ocean": "2024-08-03 02:12:59 +0500",
      "minecraft:desert": "2024-08-06 16:48:57 +0500",
      "minecraft:deep_frozen_ocean": "2024-08-03 02:54:10 +0500",
      "minecraft:jungle": "2024-07-03 01:32:21 +0500",
      "minecraft:ocean": "2024-07-03 00:42:03 +0500",
      "minecraft:snowy_beach": "2024-08-03 02:12:39 +0500",
      "minecraft:deep_lukewarm_ocean": "2024-07-15 05:49:21 +0500",
      "minecraft:flower_forest": "2024-08-03 03:21:30 +0500",
      "minecraft:old_growth_birch_forest": "2024-07-02 19:16:06 +0500",
      "minecraft:deep_dark": "2024-07-17 03:34:10 +0500",
      "minecraft:meadow": "2024-07-02 18:30:30 +0500",
      "minecraft:savanna": "2024-07-03 01:27:44 +0500",
      "minecraft:plains": "2024-07-02 19:29:09 +0500"
    },
    "done": false
  },
  "tombstone:adventure/almost_unkillable": {
    "criteria": {
      "coded_trigger": "2024-07-17 02:30:22 +0500"
    },
    "done": true
  },
  "comforts:hammock_blue_from_white": {
    "criteria": {
      "has_the_recipe": "2024-07-02 18:28:09 +0500"
    },
    "done": true
  },
  "comforts:sleeping_bag_gray_from_white": {
    "criteria": {
      "has_the_recipe": "2024-07-02 18:28:09 +0500"
    },
    "done": true
  },
  "minecolonies:production/build_cook": {
    "criteria": {
      "cook": "2024-07-17 07:20:34 +0500"
    },
    "done": true
  },
  "repurposed_structures:outposts": {
    "criteria": {
      "in_outpost_oak": "2024-07-02 21:48:52 +0500"
    },
    "done": false
  },
  "immersive_aircraft:misc/aircraftery": {
    "criteria": {
      "has_item": "2024-07-02 18:54:37 +0500"
    },
    "done": true
  },
  "minecraft:nether/brew_potion": {
    "criteria": {
      "potion": "2024-07-03 00:49:07 +0500"
    },
    "done": true
  },
  "minecolonies:minecolonies/colony_population_5": {
    "criteria": {
      "population_5": "2024-07-17 05:48:46 +0500"
    },
    "done": true
  },
  "comforts:sleeping_bag_cyan": {
    "criteria": {
      "has_the_recipe": "2024-07-02 18:28:09 +0500"
    },
    "done": true
  },
  "beautify:bookstack": {
    "criteria": {
      "requirement": "2024-07-02 18:53:18 +0500"
    },
    "done": true
  },
  "toms_storage:unlock_dia_pearl": {
    "criteria": {
      "inv_changed-ender_pearl": "2024-07-02 18:28:09 +0500",
      "inv_changed-diamond": "2024-07-02 18:28:09 +0500"
    },
    "done": true
  },
  "mcwroofs:recipes/mangrove_planks": {
    "criteria": {
      "has_planks": "2024-07-02 19:34:01 +0500"
    },
    "done": true
  },
  "idas:ancient_mines": {
    "criteria": {
      "in_ancient_mines": "2024-07-02 18:51:38 +0500"
    },
    "done": true
  },
  "repurposed_structures:ruins": {
    "criteria": {
      "in_ruins_land_cold": "2024-07-02 19:15:46 +0500"
    },
    "done": false
  },
  "minecolonies:military/root": {
    "criteria": {
      "guardtower": "2024-07-17 05:46:34 +0500"
    },
    "done": true
  },
  "comforts:hammock_purple_from_white": {
    "criteria": {
      "has_the_recipe": "2024-07-02 18:28:09 +0500"
    },
    "done": true
  },
  "mcwroofs:recipes/concrete": {
    "criteria": {
      "has_planks": "2024-07-03 01:25:54 +0500"
    },
    "done": true
  },
  "explorerscompass:explorers_compass": {
    "criteria": {
      "has_compass": "2024-07-02 18:28:09 +0500"
    },
    "done": true
  },
  "comforts:sleeping_bag_pink_from_white": {
    "criteria": {
      "has_the_recipe": "2024-07-02 18:28:10 +0500"
    },
    "done": true
  },
  "minecraft:adventure/shoot_arrow": {
    "criteria": {
      "shot_arrow": "2024-07-02 18:46:33 +0500"
    },
    "done": true
  },
  "croptopia:gather_jungle": {
    "criteria": {
      "pineapple_seed": "2024-08-03 14:43:24 +0500",
      "peanut_seed": "2024-08-03 14:43:24 +0500"
    },
    "done": false
  },
  "mcwfences:recipes/acacia": {
    "criteria": {
      "has_acacia": "2024-07-02 18:28:09 +0500"
    },
    "done": true
  },
  "croptopia:gather_desert": {
    "criteria": {
      "saguaro_seed": "2024-08-06 16:27:01 +0500"
    },
    "done": true
  },
  "mcwroofs:recipes/spruce_planks": {
    "criteria": {
      "has_planks": "2024-07-02 19:57:25 +0500"
    },
    "done": true
  },
  "comforts:sleeping_bag_yellow_from_white": {
    "criteria": {
      "has_the_recipe": "2024-07-02 18:28:09 +0500"
    },
    "done": true
  },
  "minecraft:adventure/kill_mob_near_sculk_catalyst": {
    "criteria": {
      "kill_mob_near_sculk_catalyst": "2024-07-17 03:38:02 +0500"
    },
    "done": true
  },
  "mcwroofs:recipes/andesite": {
    "criteria": {
      "has_planks": "2024-07-02 19:06:00 +0500"
    },
    "done": true
  },
  "minecraft:husbandry/fishy_business": {
    "criteria": {
      "cod": "2024-07-15 05:31:02 +0500"
    },
    "done": true
  },
  "majruszsdifficulty:recipes/misc/tattered_armor_to_cloth": {
    "criteria": {
      "has_tattered_armor": "2024-08-06 16:17:22 +0500"
    },
    "done": true
  },
  "tetra:recipes/planks": {
    "criteria": {
      "got_wood": "2024-07-02 18:38:50 +0500"
    },
    "done": true
  },
  "tetra:story/more_upgrades": {
    "criteria": {
      "hammer": "2024-07-02 23:04:47 +0500"
    },
    "done": true
  },
  "minecraft:husbandry/breed_an_animal": {
    "criteria": {
      "bred": "2024-07-17 04:59:29 +0500"
    },
    "done": true
  },
  "tombstone:adventure/choose_knowledge": {
    "criteria": {
      "coded_trigger": "2024-07-02 20:49:46 +0500"
    },
    "done": true
  },
  "farmersdelight:main/craft_knife": {
    "criteria": {
      "golden_knife": "2024-08-03 02:04:21 +0500"
    },
    "done": true
  },
  "mcwroofs:recipes/bricks": {
    "criteria": {
      "has_planks": "2024-07-17 07:48:52 +0500"
    },
    "done": true
  },
  "comforts:hammock_orange": {
    "criteria": {
      "has_the_recipe": "2024-07-02 18:28:09 +0500"
    },
    "done": true
  },
  "comforts:hammock_green_from_white": {
    "criteria": {
      "has_the_recipe": "2024-07-02 18:28:10 +0500"
    },
    "done": true
  },
  "mcwfences:recipes/dark_oak": {
    "criteria": {
      "has_dark_oak": "2024-07-02 18:28:09 +0500"
    },
    "done": true
  },
  "croptopia:pot": {
    "criteria": {
      "cooking_pot": "2024-07-16 00:28:34 +0500"
    },
    "done": true
  },
  "farmersdelight:main/place_campfire": {
    "criteria": {
      "campfire": "2024-07-16 01:22:55 +0500"
    },
    "done": true
  },
  "comforts:hammock_pink": {
    "criteria": {
      "has_the_recipe": "2024-07-02 18:28:10 +0500"
    },
    "done": true
  },
  "comforts:sleeping_bag_magenta": {
    "criteria": {
      "has_the_recipe": "2024-07-02 18:28:09 +0500"
    },
    "done": true
  },
  "minecraft:nether/explore_nether": {
    "criteria": {
      "minecraft:crimson_forest": "2024-08-03 14:51:43 +0500"
    },
    "done": false
  },
  "minecolonies:minecolonies/fulfill_request": {
    "criteria": {
      "click_gui_button_fulfill": "2024-07-16 00:55:58 +0500"
    },
    "done": true
  },
  "comforts:sleeping_bag_cyan_from_white": {
    "criteria": {
      "has_the_recipe": "2024-07-02 18:28:09 +0500"
    },
    "done": true
  },
  "mcwroofs:recipes/awning": {
    "criteria": {
      "has_planks": "2024-07-02 19:13:45 +0500"
    },
    "done": true
  },
  "mcwroofs:recipes/thatch": {
    "criteria": {
      "has_planks": "2024-07-03 01:04:56 +0500"
    },
    "done": true
  },
  "comforts:hammock_brown": {
    "criteria": {
      "has_the_recipe": "2024-07-02 18:28:09 +0500"
    },
    "done": true
  },
  "croptopia:salt": {
    "criteria": {
      "salt": "2024-07-16 01:34:12 +0500"
    },
    "done": true
  },
  "croptopia:eatcrafted": {
    "criteria": {
      "eat_crafted": "2024-07-16 00:57:26 +0500"
    },
    "done": true
  },
  "majruszsdifficulty:progressive_difficulty/undead_army": {
    "criteria": {
      "army_defeated": "2024-08-06 19:20:24 +0500"
    },
    "done": true
  },
  "minecolonies:production/build_delivery_person": {
    "criteria": {
      "delivery_person": "2024-07-20 00:33:58 +0500"
    },
    "done": true
  },
  "comforts:hammock_green": {
    "criteria": {
      "has_the_recipe": "2024-07-02 18:28:09 +0500"
    },
    "done": true
  },
  "minecraft:story/smelt_iron": {
    "criteria": {
      "iron": "2024-07-02 18:54:37 +0500"
    },
    "done": true
  },
  "meetyourfight:main/root": {
    "criteria": {
      "killed_something": "2024-07-02 18:43:07 +0500"
    },
    "done": true
  },
  "morevillagers:first_workstation_get": {
    "criteria": {
      "smithingtable": "2024-07-02 22:18:04 +0500"
    },
    "done": true
  },
  "tetra:spelunking/ancient_ruins": {
    "criteria": {
      "regular_ruin": "2024-07-02 23:53:51 +0500"
    },
    "done": true
  },
  "repurposed_structures:root": {
    "criteria": {
      "always": "2024-07-02 18:28:23 +0500"
    },
    "done": true
  },
  "tombstone:adventure/ambush": {
    "criteria": {
      "coded_trigger": "2024-07-02 20:48:36 +0500"
    },
    "done": true
  },
  "DataVersion": 3120
}